llm_github_copilot.py
llm_github_copilot-0.3.dist-info/METADATA
llm_github_copilot-0.3.dist-info/WHEEL
llm_github_copilot-0.3.dist-info/entry_points.txt
llm_github_copilot-0.3.dist-info/top_level.txt
llm_github_copilot-0.3.dist-info/RECORD
