Metadata-Version: 2.4
Name: llm-github-copilot
Version: 0.3
Summary: GitHub Copilot plugin for LLM CLI tool
Author: John M Daly
License: Apache-2.0
Project-URL: Homepage, https://github.com/jmdaly/llm-github-copilot
Project-URL: Issues, https://github.com/jmdaly/llm-github-copilot/issues
Classifier: License :: OSI Approved :: Apache Software License
Requires-Python: >=3.9
Requires-Dist: llm
Requires-Dist: httpx
Provides-Extra: test
Requires-Dist: pytest; extra == "test"
Requires-Dist: pytest-asyncio; extra == "test"
Requires-Dist: pytest-vcr; extra == "test"
Requires-Dist: vcrpy; extra == "test"
Requires-Dist: watching-testrunner; extra == "test"
